walytis_beta_embedded/__init__.py
walytis_beta_embedded-0.0.14.dist-info/METADATA
walytis_beta_embedded-0.0.14.dist-info/WHEEL
walytis_beta_embedded-0.0.14.dist-info/top_level.txt
walytis_beta_embedded-0.0.14.dist-info/RECORD
