Metadata-Version: 2.4
Name: walytis_beta_embedded
Version: 0.0.14
Summary: A lightweight, flexible, non-linear blockchain.
Author: Emendir
Project-URL: Homepage, https://github.com/emendir/Walytis_Beta
Project-URL: Documentation, https://github.com/emendir/Walytis_Beta/blob/master/docs/DocsOverview.md
Project-URL: Repository, https://github.com/emendir/Walytis_Beta.git
Project-URL: IPFS, https://ipfs.io/ipns/k2k4r8nismm5mmgrox2fci816xvj4l4cudnuc55gkfoealjuiaexbsup/Projects/Walytis
Classifier: Programming Language :: Python :: 3
Classifier: Operating System :: OS Independent
Requires-Python: >=3.11
Requires-Dist: walytis_beta>=2.4.23
